<?xml version="1.0" encoding="utf-8"?>
<message>
  <defaults>
    <data_element id="0065" value="GOVCBR"/>
    <data_element id="0051" value="UN"/>
  </defaults>
  <segment id="UNH" maxrepeat="1" required="true"/>
  <segment id="BGM" maxrepeat="1" required="true"/>
  <segment id="DTM" maxrepeat="9"/>
  <segment id="MOA" maxrepeat="1"/>
  <segment id="IFD" maxrepeat="9"/>
  <segment id="RFF" maxrepeat="99999"/>
  <segment id="CUX" maxrepeat="9"/>
  <segment id="FII" maxrepeat="1"/>
  <segment id="GPO" maxrepeat="9"/>
  <segment id="LAN" maxrepeat="1"/>
  <segment id="MEA" maxrepeat="9"/>
  <group id="SG1" maxrepeat="99">
    <segment id="LOC" maxrepeat="1" required="true"/>
    <segment id="DTM" maxrepeat="9"/>
    <segment id="ADR" maxrepeat="9"/>
    <group id="SG2" maxrepeat="99">
      <segment id="GEI" maxrepeat="1" required="true"/>
      <segment id="MOA" maxrepeat="99"/>
      <segment id="PYT" maxrepeat="99"/>
    </group>
  </group>
  <group id="SG3" maxrepeat="9">
    <segment id="GOR" maxrepeat="1" required="true"/>
    <segment id="LOC" maxrepeat="1"/>
    <segment id="DTM" maxrepeat="9"/>
    <segment id="GEI" maxrepeat="9"/>
    <group id="SG4" maxrepeat="9">
      <segment id="CTA" maxrepeat="1" required="true"/>
      <segment id="COM" maxrepeat="9"/>
    </group>
  </group>
  <group id="SG5" maxrepeat="9">
    <segment id="STS" maxrepeat="1" required="true"/>
    <segment id="DTM" maxrepeat="99"/>
    <group id="SG6" maxrepeat="99">
      <segment id="ERP" maxrepeat="1" required="true"/>
      <segment id="ELU" maxrepeat="99"/>
      <segment id="ARR" maxrepeat="99"/>
    </group>
  </group>
  <group id="SG7" maxrepeat="99">
    <segment id="NAD" maxrepeat="1" required="true"/>
    <segment id="DTM" maxrepeat="9"/>
    <segment id="GEI" maxrepeat="1"/>
    <segment id="STS" maxrepeat="1"/>
    <segment id="IFD" maxrepeat="9"/>
    <segment id="IDE" maxrepeat="9"/>
    <group id="SG8" maxrepeat="9">
      <segment id="CTA" maxrepeat="1" required="true"/>
      <segment id="COM" maxrepeat="9"/>
    </group>
  </group>
  <group id="SG9" maxrepeat="9999">
    <segment id="DOC" maxrepeat="1" required="true"/>
    <segment id="RFF" maxrepeat="9"/>
    <segment id="DTM" maxrepeat="9"/>
    <segment id="MOA" maxrepeat="9"/>
    <segment id="ALI" maxrepeat="1"/>
    <segment id="QTY" maxrepeat="99"/>
    <segment id="TSR" maxrepeat="99"/>
    <group id="SG10" maxrepeat="99">
      <segment id="NAD" maxrepeat="1" required="true"/>
      <segment id="IFD" maxrepeat="1"/>
      <segment id="IDE" maxrepeat="9"/>
      <group id="SG11" maxrepeat="9">
        <segment id="CTA" maxrepeat="1" required="true"/>
        <segment id="COM" maxrepeat="9"/>
      </group>
    </group>
    <group id="SG12" maxrepeat="99">
      <segment id="LOC" maxrepeat="1" required="true"/>
      <segment id="DTM" maxrepeat="99"/>
    </group>
  </group>
  <group id="SG13" maxrepeat="99">
    <segment id="RCS" maxrepeat="1" required="true"/>
    <segment id="FTX" maxrepeat="9"/>
    <segment id="DTM" maxrepeat="9"/>
    <segment id="GEI" maxrepeat="1"/>
    <segment id="ALI" maxrepeat="9"/>
    <group id="SG14" maxrepeat="999">
      <segment id="ERP" maxrepeat="1" required="true"/>
      <segment id="ELU" maxrepeat="99"/>
      <segment id="ARR" maxrepeat="99"/>
    </group>
  </group>
  <group id="SG15" maxrepeat="99">
    <segment id="AJT" maxrepeat="1" required="true"/>
    <segment id="FTX" maxrepeat="9"/>
    <group id="SG16" maxrepeat="999">
      <segment id="ERP" maxrepeat="1" required="true"/>
      <segment id="ELU" maxrepeat="99"/>
      <segment id="ARR" maxrepeat="99"/>
    </group>
  </group>
  <group id="SG17" maxrepeat="99">
    <segment id="ERC" maxrepeat="1" required="true"/>
    <group id="SG18" maxrepeat="999">
      <segment id="ERP" maxrepeat="1" required="true"/>
      <segment id="ELU" maxrepeat="99"/>
      <segment id="ARR" maxrepeat="99"/>
    </group>
  </group>
  <group id="SG19" maxrepeat="1">
    <segment id="INP" maxrepeat="1" required="true"/>
    <segment id="DTM" maxrepeat="9"/>
    <segment id="LOC" maxrepeat="9"/>
    <segment id="CNT" maxrepeat="99"/>
    <segment id="RSL" maxrepeat="9"/>
    <group id="SG20" maxrepeat="1">
      <segment id="NAD" maxrepeat="1" required="true"/>
      <segment id="IFD" maxrepeat="1"/>
      <segment id="DTM" maxrepeat="9"/>
      <segment id="IDE" maxrepeat="9"/>
      <group id="SG21" maxrepeat="9">
        <segment id="CTA" maxrepeat="1" required="true"/>
        <segment id="COM" maxrepeat="9"/>
      </group>
    </group>
  </group>
  <group id="SG22" maxrepeat="9">
    <segment id="GIR" maxrepeat="1" required="true"/>
    <segment id="LOC" maxrepeat="99"/>
    <segment id="VLI" maxrepeat="1"/>
    <segment id="DTM" maxrepeat="99"/>
    <segment id="MOA" maxrepeat="99"/>
    <group id="SG23" maxrepeat="9">
      <segment id="NAD" maxrepeat="1" required="true"/>
      <segment id="IFD" maxrepeat="1"/>
      <segment id="DTM" maxrepeat="9"/>
      <segment id="IDE" maxrepeat="9"/>
      <group id="SG24" maxrepeat="9">
        <segment id="CTA" maxrepeat="1" required="true"/>
        <segment id="COM" maxrepeat="9"/>
      </group>
    </group>
    <group id="SG25" maxrepeat="99">
      <segment id="PRC" maxrepeat="1" required="true"/>
      <segment id="SEQ" maxrepeat="1" required="true"/>
      <segment id="DTM" maxrepeat="9" required="true"/>
    </group>
  </group>
  <group id="SG26" maxrepeat="99">
    <segment id="TAX" maxrepeat="1" required="true"/>
    <segment id="DTM" maxrepeat="9"/>
    <segment id="ALI" maxrepeat="9"/>
    <segment id="MOA" maxrepeat="99"/>
    <segment id="QTY" maxrepeat="99"/>
    <group id="SG27" maxrepeat="9">
      <segment id="PAI" maxrepeat="1" required="true"/>
      <segment id="RFF" maxrepeat="99"/>
      <segment id="MOA" maxrepeat="99"/>
      <segment id="DTM" maxrepeat="99"/>
      <group id="SG28" maxrepeat="9">
        <segment id="GIR" maxrepeat="1" required="true"/>
        <segment id="LOC" maxrepeat="99"/>
        <segment id="VLI" maxrepeat="1"/>
        <segment id="DTM" maxrepeat="99"/>
        <segment id="MOA" maxrepeat="99"/>
        <group id="SG29" maxrepeat="1">
          <segment id="NAD" maxrepeat="1" required="true"/>
          <segment id="IFD" maxrepeat="1"/>
          <segment id="DTM" maxrepeat="9"/>
          <segment id="IDE" maxrepeat="9"/>
          <group id="SG30" maxrepeat="9">
            <segment id="CTA" maxrepeat="1" required="true"/>
            <segment id="COM" maxrepeat="9"/>
          </group>
        </group>
        <group id="SG31" maxrepeat="99">
          <segment id="PRC" maxrepeat="1" required="true"/>
          <segment id="SEQ" maxrepeat="1" required="true"/>
          <segment id="DTM" maxrepeat="9" required="true"/>
        </group>
      </group>
    </group>
  </group>
  <group id="SG32" maxrepeat="99999">
    <segment id="PAC" maxrepeat="1" required="true"/>
    <segment id="SEQ" maxrepeat="1" required="true"/>
    <segment id="PCI" maxrepeat="99"/>
    <segment id="FTX" maxrepeat="1"/>
    <segment id="GEI" maxrepeat="1"/>
    <segment id="DIM" maxrepeat="1"/>
    <segment id="MEA" maxrepeat="9"/>
  </group>
  <group id="SG33" maxrepeat="9">
    <segment id="TMP" maxrepeat="1" required="true"/>
    <segment id="MEA" maxrepeat="1"/>
    <segment id="DGS" maxrepeat="1"/>
  </group>
  <group id="SG34" maxrepeat="9">
    <segment id="TDT" maxrepeat="1" required="true"/>
    <segment id="DTM" maxrepeat="99"/>
    <segment id="RFF" maxrepeat="99"/>
    <segment id="QTY" maxrepeat="99"/>
    <segment id="MEA" maxrepeat="99"/>
    <segment id="MOA" maxrepeat="99"/>
    <segment id="POC" maxrepeat="99"/>
    <segment id="DIM" maxrepeat="99"/>
    <segment id="GDS" maxrepeat="99"/>
    <segment id="STS" maxrepeat="1"/>
    <segment id="GPO" maxrepeat="1"/>
    <segment id="GEI" maxrepeat="9"/>
    <segment id="TMD" maxrepeat="9"/>
    <segment id="COM" maxrepeat="99"/>
    <group id="SG35" maxrepeat="99">
      <segment id="SEQ" maxrepeat="1" required="true"/>
      <segment id="EVE" maxrepeat="1" required="true"/>
      <segment id="DTM" maxrepeat="9"/>
      <segment id="FTX" maxrepeat="99999" required="true"/>
    </group>
    <group id="SG36" maxrepeat="99">
      <segment id="LOC" maxrepeat="1" required="true"/>
      <segment id="SEQ" maxrepeat="1" required="true"/>
      <segment id="DTM" maxrepeat="99"/>
      <segment id="STS" maxrepeat="1"/>
      <segment id="FTX" maxrepeat="9"/>
      <segment id="GEI" maxrepeat="9"/>
      <group id="SG37" maxrepeat="99">
        <segment id="SEQ" maxrepeat="1" required="true"/>
        <segment id="EVE" maxrepeat="1" required="true"/>
        <segment id="DTM" maxrepeat="99"/>
        <segment id="FTX" maxrepeat="99"/>
        <segment id="GPO" maxrepeat="1"/>
      </group>
      <group id="SG38" maxrepeat="99">
        <segment id="ADR" maxrepeat="1" required="true"/>
        <segment id="SEQ" maxrepeat="1" required="true"/>
        <segment id="FTX" maxrepeat="9"/>
        <segment id="DTM" maxrepeat="9"/>
        <segment id="POC" maxrepeat="9"/>
        <segment id="GEI" maxrepeat="9"/>
      </group>
    </group>
    <group id="SG39" maxrepeat="99999">
      <segment id="NAD" maxrepeat="1" required="true"/>
      <segment id="SEQ" maxrepeat="1" required="true"/>
      <segment id="ATT" maxrepeat="1"/>
      <segment id="IFD" maxrepeat="1"/>
      <segment id="NAT" maxrepeat="1"/>
      <segment id="DTM" maxrepeat="99"/>
      <segment id="LOC" maxrepeat="99"/>
      <segment id="EMP" maxrepeat="99"/>
      <segment id="STS" maxrepeat="1"/>
      <segment id="GEI" maxrepeat="9"/>
      <segment id="RFF" maxrepeat="9"/>
      <segment id="IDE" maxrepeat="9"/>
      <group id="SG40" maxrepeat="99">
        <segment id="CTA" maxrepeat="1" required="true"/>
        <segment id="COM" maxrepeat="99"/>
      </group>
      <group id="SG41" maxrepeat="1">
        <segment id="ADR" maxrepeat="1" required="true"/>
        <segment id="EMP" maxrepeat="1"/>
      </group>
      <group id="SG42" maxrepeat="99">
        <segment id="DOC" maxrepeat="1" required="true"/>
        <segment id="NAD" maxrepeat="1" required="true"/>
        <segment id="DTM" maxrepeat="9"/>
        <segment id="LOC" maxrepeat="9"/>
      </group>
      <group id="SG43" maxrepeat="99">
        <segment id="SEQ" maxrepeat="1" required="true"/>
        <segment id="FTX" maxrepeat="1"/>
        <segment id="QTY" maxrepeat="1"/>
      </group>
    </group>
    <group id="SG44" maxrepeat="99999">
      <segment id="EQD" maxrepeat="1" required="true"/>
      <segment id="SEQ" maxrepeat="1" required="true"/>
      <segment id="QTY" maxrepeat="1"/>
      <segment id="GEI" maxrepeat="99"/>
      <segment id="RFF" maxrepeat="99"/>
      <segment id="RCS" maxrepeat="1"/>
      <segment id="DTM" maxrepeat="9"/>
      <group id="SG45" maxrepeat="99">
        <segment id="SEL" maxrepeat="1" required="true"/>
        <segment id="SEQ" maxrepeat="1" required="true"/>
      </group>
      <group id="SG46" maxrepeat="9">
        <segment id="NAD" maxrepeat="1" required="true"/>
        <segment id="IFD" maxrepeat="1"/>
        <segment id="DTM" maxrepeat="99"/>
        <segment id="IDE" maxrepeat="9"/>
        <group id="SG47" maxrepeat="99">
          <segment id="CTA" maxrepeat="1" required="true"/>
          <segment id="COM" maxrepeat="99"/>
        </group>
      </group>
      <group id="SG48" maxrepeat="1">
        <segment id="LOC" maxrepeat="1" required="true"/>
        <segment id="DTM" maxrepeat="99"/>
      </group>
      <group id="SG49" maxrepeat="9999">
        <segment id="SEQ" maxrepeat="1" required="true"/>
        <segment id="EQD" maxrepeat="1" required="true"/>
        <segment id="RFF" maxrepeat="99"/>
      </group>
    </group>
    <group id="SG50" maxrepeat="9999">
      <segment id="LIN" maxrepeat="1" required="true"/>
      <segment id="MEA" maxrepeat="99"/>
      <segment id="LOC" maxrepeat="99"/>
      <segment id="DTM" maxrepeat="9"/>
      <segment id="GEI" maxrepeat="9"/>
      <group id="SG51" maxrepeat="99">
        <segment id="GID" maxrepeat="1" required="true"/>
        <segment id="FTX" maxrepeat="1"/>
        <segment id="TCC" maxrepeat="99"/>
        <segment id="DGS" maxrepeat="1"/>
        <segment id="MEA" maxrepeat="99"/>
        <segment id="LOC" maxrepeat="99"/>
        <segment id="CTA" maxrepeat="99"/>
      </group>
      <group id="SG52" maxrepeat="99">
        <segment id="ADR" maxrepeat="1" required="true"/>
        <segment id="SEQ" maxrepeat="1" required="true"/>
        <segment id="DTM" maxrepeat="9"/>
      </group>
    </group>
    <group id="SG53" maxrepeat="9999">
      <segment id="CCI" maxrepeat="1" required="true"/>
      <segment id="CAV" maxrepeat="1"/>
    </group>
    <group id="SG54" maxrepeat="99">
      <segment id="SFI" maxrepeat="1" required="true"/>
      <segment id="FTX" maxrepeat="99"/>
      <group id="SG55" maxrepeat="99">
        <segment id="DOC" maxrepeat="1" required="true"/>
        <segment id="DTM" maxrepeat="9"/>
        <segment id="LOC" maxrepeat="9"/>
        <segment id="NAD" maxrepeat="9"/>
        <segment id="GEI" maxrepeat="9"/>
      </group>
    </group>
  </group>
  <segment id="UNS" maxrepeat="1" required="true"/>
  <group id="SG56" maxrepeat="9999">
    <segment id="SEQ" maxrepeat="1" required="true"/>
    <segment id="ALI" maxrepeat="99"/>
    <segment id="IFD" maxrepeat="99"/>
    <segment id="DTM" maxrepeat="99"/>
    <segment id="RFF" maxrepeat="99"/>
    <group id="SG57" maxrepeat="99">
      <segment id="NAD" maxrepeat="1" required="true"/>
      <segment id="IFD" maxrepeat="1"/>
      <segment id="DTM" maxrepeat="99"/>
      <segment id="DMS" maxrepeat="99"/>
      <segment id="IDE" maxrepeat="9"/>
      <group id="SG58" maxrepeat="99">
        <segment id="CTA" maxrepeat="1" required="true"/>
        <segment id="COM" maxrepeat="99"/>
      </group>
    </group>
    <group id="SG59" maxrepeat="99">
      <segment id="LOC" maxrepeat="1" required="true"/>
      <segment id="DTM" maxrepeat="99"/>
    </group>
    <group id="SG60" maxrepeat="999">
      <segment id="DOC" maxrepeat="1" required="true"/>
      <segment id="SEQ" maxrepeat="1" required="true"/>
      <segment id="RFF" maxrepeat="99"/>
      <segment id="DTM" maxrepeat="99"/>
      <segment id="MOA" maxrepeat="99"/>
      <segment id="ALI" maxrepeat="1"/>
      <segment id="QTY" maxrepeat="99"/>
      <segment id="TSR" maxrepeat="99"/>
      <group id="SG61" maxrepeat="9">
        <segment id="NAD" maxrepeat="1" required="true"/>
        <segment id="IFD" maxrepeat="1"/>
        <segment id="IDE" maxrepeat="9"/>
        <group id="SG62" maxrepeat="99">
          <segment id="CTA" maxrepeat="1" required="true"/>
          <segment id="COM" maxrepeat="99"/>
        </group>
      </group>
      <group id="SG63" maxrepeat="99">
        <segment id="LOC" maxrepeat="1" required="true"/>
        <segment id="DTM" maxrepeat="99"/>
      </group>
    </group>
    <group id="SG64" maxrepeat="99">
      <segment id="GEI" maxrepeat="1" required="true"/>
      <segment id="MOA" maxrepeat="99"/>
      <segment id="PYT" maxrepeat="99"/>
      <segment id="CUX" maxrepeat="1"/>
      <group id="SG65" maxrepeat="1">
        <segment id="LOC" maxrepeat="1" required="true"/>
        <segment id="DTM" maxrepeat="99"/>
      </group>
    </group>
    <group id="SG66" maxrepeat="99">
      <segment id="RCS" maxrepeat="1" required="true"/>
      <segment id="FTX" maxrepeat="9"/>
      <segment id="DTM" maxrepeat="99"/>
      <segment id="GEI" maxrepeat="99"/>
      <segment id="ALI" maxrepeat="99"/>
      <group id="SG67" maxrepeat="9">
        <segment id="ERP" maxrepeat="1" required="true"/>
        <segment id="ELU" maxrepeat="99"/>
        <segment id="ARR" maxrepeat="99"/>
      </group>
    </group>
    <group id="SG68" maxrepeat="1">
      <segment id="INP" maxrepeat="1" required="true"/>
      <segment id="DTM" maxrepeat="9"/>
      <segment id="LOC" maxrepeat="99"/>
      <segment id="CNT" maxrepeat="99"/>
      <segment id="RSL" maxrepeat="9"/>
      <group id="SG69" maxrepeat="1">
        <segment id="NAD" maxrepeat="1" required="true"/>
        <segment id="IFD" maxrepeat="1"/>
        <segment id="DTM" maxrepeat="99"/>
        <segment id="IDE" maxrepeat="9"/>
        <group id="SG70" maxrepeat="99">
          <segment id="CTA" maxrepeat="1" required="true"/>
          <segment id="COM" maxrepeat="99"/>
        </group>
      </group>
    </group>
    <group id="SG71" maxrepeat="99">
      <segment id="TAX" maxrepeat="1" required="true"/>
      <segment id="DTM" maxrepeat="99"/>
      <segment id="ALI" maxrepeat="99"/>
      <segment id="MOA" maxrepeat="99"/>
      <segment id="QTY" maxrepeat="99"/>
      <group id="SG72" maxrepeat="9">
        <segment id="PAI" maxrepeat="1" required="true"/>
        <segment id="RFF" maxrepeat="99"/>
        <segment id="MOA" maxrepeat="99"/>
        <segment id="DTM" maxrepeat="99"/>
        <group id="SG73" maxrepeat="9">
          <segment id="GIR" maxrepeat="1" required="true"/>
          <segment id="LOC" maxrepeat="99"/>
          <segment id="VLI" maxrepeat="1"/>
          <segment id="DTM" maxrepeat="99"/>
          <group id="SG74" maxrepeat="1">
            <segment id="NAD" maxrepeat="1" required="true"/>
            <segment id="IFD" maxrepeat="1"/>
            <segment id="DTM" maxrepeat="99"/>
            <segment id="IDE" maxrepeat="9"/>
            <group id="SG75" maxrepeat="99">
              <segment id="CTA" maxrepeat="1" required="true"/>
              <segment id="COM" maxrepeat="99"/>
            </group>
          </group>
        </group>
      </group>
    </group>
    <group id="SG76" maxrepeat="9">
      <segment id="GOR" maxrepeat="1" required="true"/>
      <segment id="LOC" maxrepeat="1"/>
    </group>
    <group id="SG77" maxrepeat="9">
      <segment id="MEA" maxrepeat="1" required="true"/>
      <segment id="QTY" maxrepeat="99"/>
    </group>
    <group id="SG78" maxrepeat="9">
      <segment id="STS" maxrepeat="1" required="true"/>
      <segment id="DTM" maxrepeat="99"/>
      <group id="SG79" maxrepeat="99">
        <segment id="ERP" maxrepeat="1" required="true"/>
        <segment id="ELU" maxrepeat="99"/>
      </group>
    </group>
    <group id="SG80" maxrepeat="9">
      <segment id="TMP" maxrepeat="1" required="true"/>
      <segment id="MEA" maxrepeat="99"/>
      <segment id="DGS" maxrepeat="99"/>
    </group>
    <group id="SG81" maxrepeat="1">
      <segment id="TOD" maxrepeat="1" required="true"/>
      <segment id="LOC" maxrepeat="99"/>
      <segment id="GEI" maxrepeat="99"/>
    </group>
    <group id="SG82" maxrepeat="9999">
      <segment id="CNI" maxrepeat="1" required="true"/>
      <segment id="RFF" maxrepeat="99"/>
      <segment id="GEI" maxrepeat="99"/>
      <segment id="STS" maxrepeat="99"/>
      <segment id="CNT" maxrepeat="1"/>
      <segment id="QTY" maxrepeat="99"/>
      <segment id="MOA" maxrepeat="99"/>
      <segment id="IFD" maxrepeat="99"/>
      <segment id="TOD" maxrepeat="9"/>
      <group id="SG83" maxrepeat="99">
        <segment id="NAD" maxrepeat="1" required="true"/>
        <segment id="IFD" maxrepeat="9"/>
        <segment id="DTM" maxrepeat="99"/>
        <segment id="IDE" maxrepeat="9"/>
        <group id="SG84" maxrepeat="99">
          <segment id="CTA" maxrepeat="1" required="true"/>
          <segment id="COM" maxrepeat="99"/>
        </group>
      </group>
      <group id="SG85" maxrepeat="99">
        <segment id="LOC" maxrepeat="1" required="true"/>
        <segment id="DTM" maxrepeat="99"/>
        <segment id="ARR" maxrepeat="1"/>
        <segment id="ADR" maxrepeat="9"/>
        <segment id="TPL" maxrepeat="9"/>
        <group id="SG86" maxrepeat="9">
          <segment id="GEI" maxrepeat="1" required="true"/>
          <segment id="MOA" maxrepeat="99"/>
          <segment id="PYT" maxrepeat="99"/>
        </group>
      </group>
      <group id="SG87" maxrepeat="99">
        <segment id="DOC" maxrepeat="1" required="true"/>
        <segment id="RFF" maxrepeat="99"/>
        <segment id="DTM" maxrepeat="99"/>
        <segment id="MOA" maxrepeat="99"/>
        <segment id="ALI" maxrepeat="1"/>
        <segment id="QTY" maxrepeat="99"/>
        <segment id="TSR" maxrepeat="99"/>
        <group id="SG88" maxrepeat="9">
          <segment id="NAD" maxrepeat="1" required="true"/>
          <segment id="IFD" maxrepeat="1"/>
          <segment id="IDE" maxrepeat="9"/>
          <group id="SG89" maxrepeat="99">
            <segment id="CTA" maxrepeat="1" required="true"/>
            <segment id="COM" maxrepeat="99"/>
          </group>
        </group>
        <group id="SG90" maxrepeat="99">
          <segment id="LOC" maxrepeat="1" required="true"/>
          <segment id="DTM" maxrepeat="99"/>
        </group>
      </group>
      <group id="SG91" maxrepeat="99">
        <segment id="RCS" maxrepeat="1" required="true"/>
        <segment id="FTX" maxrepeat="9"/>
        <segment id="DTM" maxrepeat="99"/>
        <segment id="GEI" maxrepeat="99"/>
        <segment id="ALI" maxrepeat="99"/>
        <group id="SG92" maxrepeat="9">
          <segment id="ERP" maxrepeat="1" required="true"/>
          <segment id="ELU" maxrepeat="99"/>
          <segment id="ARR" maxrepeat="99"/>
        </group>
      </group>
      <group id="SG93" maxrepeat="1">
        <segment id="INP" maxrepeat="1" required="true"/>
        <segment id="DTM" maxrepeat="9"/>
        <segment id="LOC" maxrepeat="99"/>
        <segment id="CNT" maxrepeat="99"/>
        <group id="SG94" maxrepeat="1">
          <segment id="NAD" maxrepeat="1" required="true"/>
          <segment id="IFD" maxrepeat="1"/>
          <segment id="DTM" maxrepeat="99"/>
          <segment id="IDE" maxrepeat="9"/>
          <group id="SG95" maxrepeat="99">
            <segment id="CTA" maxrepeat="1" required="true"/>
            <segment id="COM" maxrepeat="99"/>
          </group>
        </group>
      </group>
      <group id="SG96" maxrepeat="99">
        <segment id="PAC" maxrepeat="1" required="true"/>
        <segment id="PCI" maxrepeat="99"/>
        <segment id="FTX" maxrepeat="99"/>
        <segment id="GEI" maxrepeat="99"/>
        <segment id="DIM" maxrepeat="99"/>
        <segment id="MEA" maxrepeat="99"/>
      </group>
      <group id="SG97" maxrepeat="99">
        <segment id="TMP" maxrepeat="1" required="true"/>
        <segment id="MEA" maxrepeat="99"/>
        <segment id="DGS" maxrepeat="99"/>
      </group>
      <group id="SG98" maxrepeat="99">
        <segment id="EQD" maxrepeat="1" required="true"/>
        <segment id="SEQ" maxrepeat="1" required="true"/>
        <segment id="QTY" maxrepeat="1"/>
        <segment id="GEI" maxrepeat="99"/>
        <group id="SG99" maxrepeat="99">
          <segment id="SEL" maxrepeat="1" required="true"/>
          <segment id="SEQ" maxrepeat="1" required="true"/>
        </group>
        <group id="SG100" maxrepeat="99">
          <segment id="NAD" maxrepeat="1" required="true"/>
          <segment id="IFD" maxrepeat="1"/>
          <segment id="DTM" maxrepeat="99"/>
          <segment id="IDE" maxrepeat="9"/>
          <group id="SG101" maxrepeat="99">
            <segment id="CTA" maxrepeat="1" required="true"/>
            <segment id="COM" maxrepeat="99"/>
          </group>
        </group>
      </group>
      <group id="SG102" maxrepeat="99">
        <segment id="TDT" maxrepeat="1" required="true"/>
        <segment id="DTM" maxrepeat="99"/>
        <segment id="RFF" maxrepeat="99"/>
        <segment id="QTY" maxrepeat="99"/>
        <segment id="MEA" maxrepeat="99"/>
        <segment id="MOA" maxrepeat="99"/>
        <segment id="POC" maxrepeat="99"/>
        <segment id="DIM" maxrepeat="99"/>
        <segment id="FTX" maxrepeat="99"/>
        <segment id="GDS" maxrepeat="99"/>
        <segment id="STS" maxrepeat="1"/>
        <segment id="GPO" maxrepeat="1"/>
        <segment id="GEI" maxrepeat="9"/>
        <group id="SG103" maxrepeat="99">
          <segment id="LOC" maxrepeat="1" required="true"/>
          <segment id="SEQ" maxrepeat="1" required="true"/>
          <segment id="DTM" maxrepeat="99"/>
        </group>
        <group id="SG104" maxrepeat="99">
          <segment id="NAD" maxrepeat="1" required="true"/>
          <segment id="IFD" maxrepeat="1"/>
          <segment id="NAT" maxrepeat="1"/>
          <segment id="DTM" maxrepeat="99"/>
          <segment id="IDE" maxrepeat="9"/>
          <group id="SG105" maxrepeat="99">
            <segment id="CTA" maxrepeat="1" required="true"/>
            <segment id="COM" maxrepeat="99"/>
          </group>
        </group>
        <group id="SG106" maxrepeat="99">
          <segment id="EQD" maxrepeat="1" required="true"/>
          <segment id="SEQ" maxrepeat="1" required="true"/>
          <segment id="QTY" maxrepeat="1"/>
          <segment id="GEI" maxrepeat="99"/>
          <group id="SG107" maxrepeat="99">
            <segment id="SEL" maxrepeat="1" required="true"/>
            <segment id="SEQ" maxrepeat="1" required="true"/>
          </group>
          <group id="SG108" maxrepeat="9">
            <segment id="NAD" maxrepeat="1" required="true"/>
            <segment id="IFD" maxrepeat="1"/>
            <segment id="DTM" maxrepeat="99"/>
            <segment id="IDE" maxrepeat="9"/>
            <group id="SG109" maxrepeat="99">
              <segment id="CTA" maxrepeat="1" required="true"/>
              <segment id="COM" maxrepeat="99"/>
            </group>
          </group>
        </group>
      </group>
    </group>
    <group id="SG110" maxrepeat="99">
      <segment id="ARD" maxrepeat="1" required="true"/>
      <segment id="MOA" maxrepeat="99"/>
      <segment id="GEI" maxrepeat="99"/>
      <segment id="PCD" maxrepeat="99"/>
    </group>
    <group id="SG111" maxrepeat="9999">
      <segment id="LIN" maxrepeat="1" required="true"/>
      <segment id="MOA" maxrepeat="99"/>
      <segment id="IFD" maxrepeat="99"/>
      <segment id="STS" maxrepeat="9"/>
      <segment id="ALI" maxrepeat="99"/>
      <segment id="RFF" maxrepeat="9"/>
      <group id="SG112" maxrepeat="99">
        <segment id="NAD" maxrepeat="1" required="true"/>
        <segment id="IFD" maxrepeat="9"/>
        <segment id="DTM" maxrepeat="99"/>
        <segment id="IDE" maxrepeat="9"/>
        <group id="SG113" maxrepeat="99">
          <segment id="CTA" maxrepeat="1" required="true"/>
          <segment id="COM" maxrepeat="99"/>
        </group>
      </group>
      <group id="SG114" maxrepeat="99">
        <segment id="LOC" maxrepeat="1" required="true"/>
        <segment id="DTM" maxrepeat="99"/>
        <segment id="FTX" maxrepeat="9"/>
        <segment id="ADR" maxrepeat="9"/>
      </group>
      <group id="SG115" maxrepeat="99">
        <segment id="DOC" maxrepeat="1" required="true"/>
        <segment id="RFF" maxrepeat="99"/>
        <segment id="DTM" maxrepeat="99"/>
        <segment id="MOA" maxrepeat="99"/>
        <segment id="ALI" maxrepeat="1"/>
        <segment id="QTY" maxrepeat="99"/>
        <segment id="TSR" maxrepeat="99"/>
        <segment id="GEI" maxrepeat="9"/>
        <group id="SG116" maxrepeat="99">
          <segment id="NAD" maxrepeat="1" required="true"/>
          <segment id="IFD" maxrepeat="1"/>
          <segment id="IDE" maxrepeat="9"/>
          <group id="SG117" maxrepeat="99">
            <segment id="CTA" maxrepeat="1" required="true"/>
            <segment id="COM" maxrepeat="99"/>
          </group>
        </group>
        <group id="SG118" maxrepeat="99">
          <segment id="LOC" maxrepeat="1" required="true"/>
          <segment id="DTM" maxrepeat="99"/>
        </group>
      </group>
      <group id="SG119" maxrepeat="99">
        <segment id="RCS" maxrepeat="1" required="true"/>
        <segment id="FTX" maxrepeat="9"/>
        <segment id="DTM" maxrepeat="99"/>
        <segment id="GEI" maxrepeat="99"/>
        <segment id="ALI" maxrepeat="99"/>
        <group id="SG120" maxrepeat="99">
          <segment id="ERP" maxrepeat="1" required="true"/>
          <segment id="ELU" maxrepeat="99"/>
          <segment id="ARR" maxrepeat="99"/>
        </group>
      </group>
      <group id="SG121" maxrepeat="1">
        <segment id="INP" maxrepeat="1" required="true"/>
        <segment id="DTM" maxrepeat="9"/>
        <segment id="LOC" maxrepeat="99"/>
        <segment id="CNT" maxrepeat="9"/>
        <group id="SG122" maxrepeat="1">
          <segment id="NAD" maxrepeat="1" required="true"/>
          <segment id="IFD" maxrepeat="1"/>
          <segment id="DTM" maxrepeat="99"/>
          <segment id="IDE" maxrepeat="9"/>
          <group id="SG123" maxrepeat="99">
            <segment id="CTA" maxrepeat="1" required="true"/>
            <segment id="COM" maxrepeat="99"/>
          </group>
        </group>
      </group>
      <group id="SG124" maxrepeat="99">
        <segment id="MEA" maxrepeat="1" required="true"/>
        <segment id="QTY" maxrepeat="99"/>
      </group>
      <group id="SG125" maxrepeat="999">
        <segment id="PAC" maxrepeat="1" required="true"/>
        <segment id="SEQ" maxrepeat="1" required="true"/>
        <segment id="PCI" maxrepeat="99"/>
        <segment id="FTX" maxrepeat="99"/>
        <segment id="GEI" maxrepeat="99"/>
        <segment id="DIM" maxrepeat="99"/>
        <segment id="MEA" maxrepeat="99"/>
      </group>
      <group id="SG126" maxrepeat="99">
        <segment id="ARD" maxrepeat="1" required="true"/>
        <segment id="MOA" maxrepeat="99"/>
        <segment id="GEI" maxrepeat="99"/>
        <segment id="PCD" maxrepeat="99"/>
      </group>
      <group id="SG127" maxrepeat="99">
        <segment id="GID" maxrepeat="1" required="true"/>
        <segment id="IMD" maxrepeat="99"/>
        <segment id="APP" maxrepeat="99"/>
        <segment id="FTX" maxrepeat="99"/>
        <segment id="RFF" maxrepeat="99"/>
        <segment id="DTM" maxrepeat="99"/>
        <segment id="GIR" maxrepeat="99"/>
        <segment id="GIN" maxrepeat="99"/>
        <segment id="GEI" maxrepeat="99"/>
        <segment id="MEA" maxrepeat="99"/>
        <segment id="MOA" maxrepeat="99"/>
        <segment id="CDI" maxrepeat="99"/>
        <segment id="PGI" maxrepeat="99"/>
        <segment id="TCC" maxrepeat="99"/>
        <segment id="CNT" maxrepeat="99"/>
        <segment id="IFD" maxrepeat="99"/>
        <segment id="TDT" maxrepeat="9"/>
        <group id="SG128" maxrepeat="99">
          <segment id="LOC" maxrepeat="1" required="true"/>
          <segment id="SEQ" maxrepeat="1" required="true"/>
          <segment id="DTM" maxrepeat="99"/>
        </group>
        <group id="SG129" maxrepeat="99">
          <segment id="NAD" maxrepeat="1" required="true"/>
          <segment id="IFD" maxrepeat="9"/>
          <segment id="DTM" maxrepeat="99"/>
          <segment id="IDE" maxrepeat="9"/>
          <group id="SG130" maxrepeat="99">
            <segment id="CTA" maxrepeat="1" required="true"/>
            <segment id="COM" maxrepeat="99"/>
          </group>
        </group>
        <group id="SG131" maxrepeat="99">
          <segment id="DOC" maxrepeat="1" required="true"/>
          <segment id="RFF" maxrepeat="99"/>
          <segment id="DTM" maxrepeat="99"/>
          <segment id="MOA" maxrepeat="99"/>
          <segment id="ALI" maxrepeat="1"/>
          <segment id="QTY" maxrepeat="99"/>
          <segment id="TSR" maxrepeat="99"/>
          <segment id="GEI" maxrepeat="9"/>
          <segment id="GIN" maxrepeat="99"/>
          <segment id="GIR" maxrepeat="99"/>
          <segment id="IMD" maxrepeat="99"/>
          <group id="SG132" maxrepeat="99">
            <segment id="NAD" maxrepeat="1" required="true"/>
            <segment id="IFD" maxrepeat="1"/>
            <segment id="IDE" maxrepeat="9"/>
            <group id="SG133" maxrepeat="99">
              <segment id="CTA" maxrepeat="1" required="true"/>
              <segment id="COM" maxrepeat="99"/>
            </group>
          </group>
          <group id="SG134" maxrepeat="99">
            <segment id="LOC" maxrepeat="1" required="true"/>
            <segment id="DTM" maxrepeat="99"/>
          </group>
        </group>
        <group id="SG135" maxrepeat="99">
          <segment id="RCS" maxrepeat="1" required="true"/>
          <segment id="FTX" maxrepeat="9"/>
          <segment id="DTM" maxrepeat="99"/>
          <segment id="GEI" maxrepeat="99"/>
          <segment id="ALI" maxrepeat="99"/>
          <group id="SG136" maxrepeat="99">
            <segment id="ERP" maxrepeat="1" required="true"/>
            <segment id="ELU" maxrepeat="99"/>
            <segment id="ARR" maxrepeat="99"/>
          </group>
        </group>
        <group id="SG137" maxrepeat="999">
          <segment id="PAC" maxrepeat="1" required="true"/>
          <segment id="PCI" maxrepeat="99"/>
          <segment id="FTX" maxrepeat="99"/>
          <segment id="GEI" maxrepeat="99"/>
          <segment id="DIM" maxrepeat="99"/>
          <segment id="MEA" maxrepeat="99"/>
        </group>
        <group id="SG138" maxrepeat="99">
          <segment id="COD" maxrepeat="1" required="true"/>
          <segment id="QTY" maxrepeat="99"/>
          <segment id="PCD" maxrepeat="99"/>
          <segment id="GEI" maxrepeat="99"/>
          <segment id="LOC" maxrepeat="9"/>
        </group>
        <group id="SG139" maxrepeat="1">
          <segment id="INP" maxrepeat="1" required="true"/>
          <segment id="DTM" maxrepeat="9"/>
          <segment id="LOC" maxrepeat="99"/>
          <segment id="CNT" maxrepeat="99"/>
          <group id="SG140" maxrepeat="1">
            <segment id="NAD" maxrepeat="1" required="true"/>
            <segment id="IFD" maxrepeat="1"/>
            <segment id="DTM" maxrepeat="99"/>
            <segment id="IDE" maxrepeat="9"/>
            <group id="SG141" maxrepeat="99">
              <segment id="CTA" maxrepeat="1" required="true"/>
              <segment id="COM" maxrepeat="99"/>
            </group>
          </group>
        </group>
        <group id="SG142" maxrepeat="99">
          <segment id="TAX" maxrepeat="1" required="true"/>
          <segment id="DTM" maxrepeat="99"/>
          <segment id="ALI" maxrepeat="99"/>
          <segment id="MOA" maxrepeat="99"/>
          <segment id="QTY" maxrepeat="99"/>
          <segment id="TCC" maxrepeat="9"/>
          <segment id="FTX" maxrepeat="9"/>
          <group id="SG143" maxrepeat="99">
            <segment id="PAI" maxrepeat="1" required="true"/>
            <segment id="RFF" maxrepeat="99"/>
            <segment id="MOA" maxrepeat="99"/>
            <segment id="DTM" maxrepeat="99"/>
            <group id="SG144" maxrepeat="99">
              <segment id="GIR" maxrepeat="1" required="true"/>
              <segment id="LOC" maxrepeat="99"/>
              <segment id="VLI" maxrepeat="1"/>
              <segment id="DTM" maxrepeat="99"/>
              <segment id="MOA" maxrepeat="99"/>
              <group id="SG145" maxrepeat="99">
                <segment id="NAD" maxrepeat="1" required="true"/>
                <segment id="IFD" maxrepeat="1"/>
                <segment id="DTM" maxrepeat="99"/>
                <segment id="IDE" maxrepeat="9"/>
                <group id="SG146" maxrepeat="99">
                  <segment id="CTA" maxrepeat="1" required="true"/>
                  <segment id="COM" maxrepeat="99"/>
                </group>
              </group>
              <group id="SG147" maxrepeat="9">
                <segment id="ARR" maxrepeat="1" required="true"/>
                <segment id="DTM" maxrepeat="9" required="true"/>
              </group>
            </group>
          </group>
          <group id="SG148" maxrepeat="99">
            <segment id="CUX" maxrepeat="1" required="true"/>
            <segment id="SEQ" maxrepeat="1" required="true"/>
            <segment id="MOA" maxrepeat="9" required="true"/>
          </group>
          <group id="SG149" maxrepeat="99">
            <segment id="PCD" maxrepeat="1" required="true"/>
            <segment id="TCC" maxrepeat="9"/>
            <group id="SG150" maxrepeat="99">
              <segment id="QTY" maxrepeat="1" required="true"/>
              <segment id="CUX" maxrepeat="9"/>
            </group>
          </group>
        </group>
        <group id="SG151" maxrepeat="99">
          <segment id="DLI" maxrepeat="1" required="true"/>
          <segment id="MOA" maxrepeat="99"/>
        </group>
        <group id="SG152" maxrepeat="99">
          <segment id="STS" maxrepeat="1" required="true"/>
          <segment id="DTM" maxrepeat="99"/>
          <group id="SG153" maxrepeat="99">
            <segment id="ERP" maxrepeat="1" required="true"/>
            <segment id="ELU" maxrepeat="99"/>
          </group>
        </group>
        <group id="SG154" maxrepeat="99">
          <segment id="TMP" maxrepeat="1" required="true"/>
          <segment id="MEA" maxrepeat="99"/>
          <segment id="DGS" maxrepeat="99"/>
        </group>
        <group id="SG155" maxrepeat="99">
          <segment id="EQD" maxrepeat="1" required="true"/>
          <segment id="SEQ" maxrepeat="1" required="true"/>
        </group>
        <group id="SG156" maxrepeat="99">
          <segment id="PRC" maxrepeat="1" required="true"/>
          <segment id="SEQ" maxrepeat="1" required="true"/>
          <segment id="TMP" maxrepeat="9"/>
          <segment id="DTM" maxrepeat="9"/>
          <group id="SG157" maxrepeat="99">
            <segment id="NAD" maxrepeat="1" required="true"/>
            <segment id="IFD" maxrepeat="1"/>
            <segment id="IDE" maxrepeat="9"/>
            <group id="SG158" maxrepeat="99">
              <segment id="CTA" maxrepeat="1" required="true"/>
              <segment id="COM" maxrepeat="99"/>
            </group>
          </group>
        </group>
        <group id="SG159" maxrepeat="9">
          <segment id="ATT" maxrepeat="1" required="true"/>
          <segment id="DGS" maxrepeat="1" required="true"/>
          <segment id="FTX" maxrepeat="9"/>
          <group id="SG160" maxrepeat="9">
            <segment id="NAD" maxrepeat="1" required="true"/>
            <segment id="IFD" maxrepeat="9"/>
            <segment id="IDE" maxrepeat="9"/>
            <group id="SG161" maxrepeat="9">
              <segment id="CTA" maxrepeat="1" required="true"/>
              <segment id="COM" maxrepeat="9"/>
            </group>
          </group>
        </group>
      </group>
      <group id="SG162" maxrepeat="99">
        <segment id="PYT" maxrepeat="1" required="true"/>
        <segment id="GEI" maxrepeat="9"/>
        <segment id="MOA" maxrepeat="99"/>
        <segment id="CUX" maxrepeat="1"/>
        <group id="SG163" maxrepeat="1">
          <segment id="LOC" maxrepeat="1" required="true"/>
          <segment id="DTM" maxrepeat="99"/>
        </group>
      </group>
    </group>
  </group>
  <segment id="HYN" maxrepeat="1" required="true"/>
  <group id="SG164" maxrepeat="9999">
    <segment id="CNI" maxrepeat="1" required="true"/>
    <segment id="RFF" maxrepeat="99"/>
    <segment id="GEI" maxrepeat="99"/>
    <segment id="STS" maxrepeat="99"/>
    <segment id="MEA" maxrepeat="1"/>
    <segment id="QTY" maxrepeat="99"/>
    <segment id="MOA" maxrepeat="99"/>
    <segment id="IFD" maxrepeat="99"/>
    <segment id="HAN" maxrepeat="1"/>
    <segment id="CNT" maxrepeat="9"/>
    <segment id="DTM" maxrepeat="9"/>
    <group id="SG165" maxrepeat="99">
      <segment id="NAD" maxrepeat="1" required="true"/>
      <segment id="IFD" maxrepeat="99"/>
      <segment id="DTM" maxrepeat="99"/>
      <segment id="DMS" maxrepeat="99"/>
      <segment id="IDE" maxrepeat="9"/>
      <group id="SG166" maxrepeat="99">
        <segment id="CTA" maxrepeat="1" required="true"/>
        <segment id="COM" maxrepeat="99"/>
      </group>
    </group>
    <group id="SG167" maxrepeat="99">
      <segment id="LOC" maxrepeat="1" required="true"/>
      <segment id="SEQ" maxrepeat="1" required="true"/>
      <segment id="DTM" maxrepeat="99"/>
      <segment id="ADR" maxrepeat="9"/>
      <segment id="TPL" maxrepeat="9"/>
      <segment id="GEI" maxrepeat="9"/>
    </group>
    <group id="SG168" maxrepeat="99">
      <segment id="DOC" maxrepeat="1" required="true"/>
      <segment id="RFF" maxrepeat="99"/>
      <segment id="DTM" maxrepeat="99"/>
      <segment id="MOA" maxrepeat="99"/>
      <segment id="ALI" maxrepeat="1"/>
      <segment id="QTY" maxrepeat="99"/>
      <segment id="TSR" maxrepeat="99"/>
      <group id="SG169" maxrepeat="99">
        <segment id="NAD" maxrepeat="1" required="true"/>
        <segment id="IFD" maxrepeat="1"/>
        <segment id="IDE" maxrepeat="9"/>
        <group id="SG170" maxrepeat="99">
          <segment id="CTA" maxrepeat="1" required="true"/>
          <segment id="COM" maxrepeat="99"/>
        </group>
      </group>
      <group id="SG171" maxrepeat="99">
        <segment id="LOC" maxrepeat="1" required="true"/>
        <segment id="DTM" maxrepeat="99"/>
      </group>
    </group>
    <group id="SG172" maxrepeat="99">
      <segment id="RCS" maxrepeat="1" required="true"/>
      <segment id="FTX" maxrepeat="9"/>
      <segment id="DTM" maxrepeat="99"/>
      <segment id="GEI" maxrepeat="99"/>
      <segment id="ALI" maxrepeat="99"/>
      <group id="SG173" maxrepeat="99">
        <segment id="ERP" maxrepeat="1" required="true"/>
        <segment id="ELU" maxrepeat="99"/>
        <segment id="ARR" maxrepeat="99"/>
      </group>
    </group>
    <group id="SG174" maxrepeat="1">
      <segment id="INP" maxrepeat="1" required="true"/>
      <segment id="DTM" maxrepeat="9"/>
      <segment id="LOC" maxrepeat="99"/>
      <segment id="CNT" maxrepeat="99"/>
      <segment id="FTX" maxrepeat="9"/>
      <group id="SG175" maxrepeat="1">
        <segment id="NAD" maxrepeat="1" required="true"/>
        <segment id="IFD" maxrepeat="1"/>
        <segment id="DTM" maxrepeat="99"/>
        <segment id="IDE" maxrepeat="9"/>
        <group id="SG176" maxrepeat="99">
          <segment id="CTA" maxrepeat="1" required="true"/>
          <segment id="COM" maxrepeat="99"/>
        </group>
      </group>
    </group>
    <group id="SG177" maxrepeat="99">
      <segment id="TOD" maxrepeat="1" required="true"/>
      <segment id="RTE" maxrepeat="1"/>
      <segment id="MOA" maxrepeat="1"/>
    </group>
    <group id="SG178" maxrepeat="9">
      <segment id="PAC" maxrepeat="1" required="true"/>
      <segment id="PCI" maxrepeat="99"/>
      <segment id="FTX" maxrepeat="99"/>
      <segment id="GEI" maxrepeat="99"/>
      <segment id="DIM" maxrepeat="99"/>
      <segment id="MEA" maxrepeat="99"/>
    </group>
    <group id="SG179" maxrepeat="99">
      <segment id="TMP" maxrepeat="1" required="true"/>
      <segment id="MEA" maxrepeat="99"/>
      <segment id="DGS" maxrepeat="99"/>
    </group>
    <group id="SG180" maxrepeat="99">
      <segment id="RSL" maxrepeat="1" required="true"/>
      <segment id="QTY" maxrepeat="99"/>
      <segment id="DTM" maxrepeat="99"/>
    </group>
    <group id="SG181" maxrepeat="1">
      <segment id="GOR" maxrepeat="1" required="true"/>
      <segment id="LOC" maxrepeat="1"/>
    </group>
    <group id="SG182" maxrepeat="9999">
      <segment id="EQD" maxrepeat="1" required="true"/>
      <segment id="SEQ" maxrepeat="1" required="true"/>
      <segment id="QTY" maxrepeat="1"/>
      <segment id="MEA" maxrepeat="9"/>
      <segment id="GEI" maxrepeat="99"/>
      <segment id="TSR" maxrepeat="99"/>
      <group id="SG183" maxrepeat="99">
        <segment id="SEL" maxrepeat="1" required="true"/>
        <segment id="SEQ" maxrepeat="1" required="true"/>
      </group>
      <group id="SG184" maxrepeat="99">
        <segment id="NAD" maxrepeat="1" required="true"/>
        <segment id="IFD" maxrepeat="1"/>
        <segment id="DTM" maxrepeat="99"/>
        <segment id="IDE" maxrepeat="9"/>
        <group id="SG185" maxrepeat="99">
          <segment id="CTA" maxrepeat="1" required="true"/>
          <segment id="COM" maxrepeat="99"/>
        </group>
      </group>
      <group id="SG186" maxrepeat="9">
        <segment id="LOC" maxrepeat="1" required="true"/>
        <segment id="DTM" maxrepeat="99"/>
      </group>
      <group id="SG187" maxrepeat="99">
        <segment id="DOC" maxrepeat="1" required="true"/>
        <segment id="DTM" maxrepeat="99"/>
        <segment id="MOA" maxrepeat="99"/>
        <segment id="GEI" maxrepeat="9"/>
        <group id="SG188" maxrepeat="99">
          <segment id="NAD" maxrepeat="1" required="true"/>
          <segment id="IFD" maxrepeat="1"/>
          <segment id="IDE" maxrepeat="9"/>
          <group id="SG189" maxrepeat="99">
            <segment id="CTA" maxrepeat="1" required="true"/>
            <segment id="COM" maxrepeat="99"/>
          </group>
        </group>
        <group id="SG190" maxrepeat="1">
          <segment id="LOC" maxrepeat="1" required="true"/>
          <segment id="DTM" maxrepeat="99"/>
        </group>
      </group>
    </group>
    <group id="SG191" maxrepeat="99">
      <segment id="TDT" maxrepeat="1" required="true"/>
      <segment id="DTM" maxrepeat="99"/>
      <segment id="RFF" maxrepeat="99"/>
      <segment id="QTY" maxrepeat="99"/>
      <segment id="MEA" maxrepeat="99"/>
      <segment id="MOA" maxrepeat="99"/>
      <segment id="POC" maxrepeat="99"/>
      <segment id="DIM" maxrepeat="99"/>
      <segment id="FTX" maxrepeat="99"/>
      <segment id="GDS" maxrepeat="99"/>
      <segment id="STS" maxrepeat="1"/>
      <segment id="GPO" maxrepeat="1"/>
      <group id="SG192" maxrepeat="99">
        <segment id="LOC" maxrepeat="1" required="true"/>
        <segment id="SEQ" maxrepeat="1" required="true"/>
        <segment id="DTM" maxrepeat="99"/>
      </group>
      <group id="SG193" maxrepeat="99">
        <segment id="NAD" maxrepeat="1" required="true"/>
        <segment id="IFD" maxrepeat="1"/>
        <segment id="NAT" maxrepeat="1"/>
        <segment id="DTM" maxrepeat="99"/>
        <segment id="LOC" maxrepeat="99"/>
        <segment id="EMP" maxrepeat="99"/>
        <segment id="IDE" maxrepeat="9"/>
        <group id="SG194" maxrepeat="99">
          <segment id="CTA" maxrepeat="1" required="true"/>
          <segment id="COM" maxrepeat="99"/>
        </group>
        <group id="SG195" maxrepeat="99">
          <segment id="ADR" maxrepeat="1" required="true"/>
          <segment id="EMP" maxrepeat="1"/>
        </group>
      </group>
      <group id="SG196" maxrepeat="99">
        <segment id="DOC" maxrepeat="1" required="true"/>
        <segment id="RFF" maxrepeat="99"/>
        <segment id="DTM" maxrepeat="99"/>
        <segment id="MOA" maxrepeat="99"/>
        <segment id="ALI" maxrepeat="1"/>
        <segment id="QTY" maxrepeat="99"/>
        <segment id="TSR" maxrepeat="99"/>
        <segment id="GEI" maxrepeat="9"/>
        <group id="SG197" maxrepeat="99">
          <segment id="NAD" maxrepeat="1" required="true"/>
          <segment id="IFD" maxrepeat="1"/>
          <segment id="IDE" maxrepeat="9"/>
          <group id="SG198" maxrepeat="99">
            <segment id="CTA" maxrepeat="1" required="true"/>
            <segment id="COM" maxrepeat="99"/>
          </group>
        </group>
        <group id="SG199" maxrepeat="99">
          <segment id="LOC" maxrepeat="1" required="true"/>
          <segment id="DTM" maxrepeat="99"/>
        </group>
        <group id="SG200" maxrepeat="99">
          <segment id="AJT" maxrepeat="1" required="true"/>
          <group id="SG201" maxrepeat="99">
            <segment id="ERP" maxrepeat="1" required="true"/>
            <segment id="ELU" maxrepeat="99"/>
          </group>
        </group>
      </group>
      <group id="SG202" maxrepeat="99">
        <segment id="EQD" maxrepeat="1" required="true"/>
        <segment id="SEQ" maxrepeat="1" required="true"/>
        <segment id="QTY" maxrepeat="1"/>
        <segment id="GEI" maxrepeat="99"/>
        <group id="SG203" maxrepeat="99">
          <segment id="SEL" maxrepeat="1" required="true"/>
          <segment id="SEQ" maxrepeat="1" required="true"/>
        </group>
        <group id="SG204" maxrepeat="99">
          <segment id="NAD" maxrepeat="1" required="true"/>
          <segment id="IFD" maxrepeat="1"/>
          <segment id="DTM" maxrepeat="99"/>
          <segment id="IDE" maxrepeat="9"/>
          <group id="SG205" maxrepeat="99">
            <segment id="CTA" maxrepeat="1" required="true"/>
            <segment id="COM" maxrepeat="99"/>
          </group>
        </group>
        <group id="SG206" maxrepeat="99">
          <segment id="LOC" maxrepeat="1" required="true"/>
          <segment id="DTM" maxrepeat="99"/>
        </group>
      </group>
      <group id="SG207" maxrepeat="9999">
        <segment id="CCI" maxrepeat="1" required="true"/>
        <segment id="CAV" maxrepeat="1"/>
      </group>
    </group>
    <group id="SG208" maxrepeat="9999">
      <segment id="SEQ" maxrepeat="1" required="true"/>
      <segment id="GEI" maxrepeat="99"/>
      <segment id="STS" maxrepeat="99"/>
      <segment id="RFF" maxrepeat="99"/>
      <segment id="IFD" maxrepeat="99"/>
      <segment id="HAN" maxrepeat="99"/>
      <segment id="TDT" maxrepeat="9"/>
      <group id="SG209" maxrepeat="99">
        <segment id="NAD" maxrepeat="1" required="true"/>
        <segment id="IFD" maxrepeat="1"/>
        <segment id="DTM" maxrepeat="99"/>
        <segment id="IDE" maxrepeat="9"/>
        <group id="SG210" maxrepeat="99">
          <segment id="CTA" maxrepeat="1" required="true"/>
          <segment id="COM" maxrepeat="99"/>
        </group>
      </group>
      <group id="SG211" maxrepeat="99">
        <segment id="LOC" maxrepeat="1" required="true"/>
        <segment id="DTM" maxrepeat="99"/>
        <segment id="ADR" maxrepeat="9"/>
      </group>
      <group id="SG212" maxrepeat="99">
        <segment id="DOC" maxrepeat="1" required="true"/>
        <segment id="RFF" maxrepeat="99"/>
        <segment id="DTM" maxrepeat="99"/>
        <segment id="MOA" maxrepeat="99"/>
        <segment id="ALI" maxrepeat="1"/>
        <segment id="QTY" maxrepeat="99"/>
        <segment id="TSR" maxrepeat="99"/>
        <group id="SG213" maxrepeat="99">
          <segment id="NAD" maxrepeat="1" required="true"/>
          <segment id="IFD" maxrepeat="1"/>
          <segment id="IDE" maxrepeat="9"/>
          <group id="SG214" maxrepeat="99">
            <segment id="CTA" maxrepeat="1" required="true"/>
            <segment id="COM" maxrepeat="99"/>
          </group>
        </group>
        <group id="SG215" maxrepeat="99">
          <segment id="LOC" maxrepeat="1" required="true"/>
          <segment id="DTM" maxrepeat="99"/>
        </group>
        <group id="SG216" maxrepeat="99">
          <segment id="AJT" maxrepeat="1" required="true"/>
          <group id="SG217" maxrepeat="99">
            <segment id="ERP" maxrepeat="1" required="true"/>
            <segment id="ELU" maxrepeat="99"/>
          </group>
        </group>
      </group>
      <group id="SG218" maxrepeat="99">
        <segment id="RCS" maxrepeat="1" required="true"/>
        <segment id="FTX" maxrepeat="9"/>
        <segment id="DTM" maxrepeat="99"/>
        <segment id="GEI" maxrepeat="99"/>
        <segment id="ALI" maxrepeat="99"/>
        <group id="SG219" maxrepeat="99">
          <segment id="ERP" maxrepeat="1" required="true"/>
          <segment id="ELU" maxrepeat="99"/>
          <segment id="ARR" maxrepeat="99"/>
        </group>
      </group>
      <group id="SG220" maxrepeat="99">
        <segment id="INP" maxrepeat="1" required="true"/>
        <segment id="DTM" maxrepeat="9"/>
        <segment id="LOC" maxrepeat="99"/>
        <segment id="CNT" maxrepeat="99"/>
        <group id="SG221" maxrepeat="1">
          <segment id="NAD" maxrepeat="1" required="true"/>
          <segment id="IFD" maxrepeat="1"/>
          <segment id="DTM" maxrepeat="99"/>
          <segment id="IDE" maxrepeat="9"/>
          <group id="SG222" maxrepeat="99">
            <segment id="CTA" maxrepeat="1" required="true"/>
            <segment id="COM" maxrepeat="99"/>
          </group>
        </group>
      </group>
      <group id="SG223" maxrepeat="99">
        <segment id="MEA" maxrepeat="1" required="true"/>
        <segment id="QTY" maxrepeat="99"/>
        <segment id="PCD" maxrepeat="1"/>
      </group>
      <group id="SG224" maxrepeat="999">
        <segment id="PAC" maxrepeat="1" required="true"/>
        <segment id="SEQ" maxrepeat="1" required="true"/>
        <segment id="PCI" maxrepeat="99"/>
        <segment id="FTX" maxrepeat="99"/>
        <segment id="GEI" maxrepeat="99"/>
        <segment id="DIM" maxrepeat="99"/>
        <segment id="MEA" maxrepeat="99"/>
        <group id="SG225" maxrepeat="99">
          <segment id="NAD" maxrepeat="1" required="true"/>
          <segment id="IFD" maxrepeat="1"/>
          <segment id="DTM" maxrepeat="99"/>
          <segment id="IDE" maxrepeat="9"/>
          <group id="SG226" maxrepeat="99">
            <segment id="CTA" maxrepeat="1" required="true"/>
            <segment id="COM" maxrepeat="99"/>
          </group>
        </group>
      </group>
      <group id="SG227" maxrepeat="99">
        <segment id="TMP" maxrepeat="1" required="true"/>
        <segment id="MEA" maxrepeat="99"/>
        <segment id="DGS" maxrepeat="99"/>
      </group>
      <group id="SG228" maxrepeat="9999">
        <segment id="EQD" maxrepeat="1" required="true"/>
        <segment id="SEQ" maxrepeat="1" required="true"/>
        <segment id="QTY" maxrepeat="1"/>
        <segment id="MEA" maxrepeat="9"/>
        <segment id="GEI" maxrepeat="99"/>
        <group id="SG229" maxrepeat="99">
          <segment id="SEL" maxrepeat="1" required="true"/>
          <segment id="SEQ" maxrepeat="1" required="true"/>
        </group>
        <group id="SG230" maxrepeat="99">
          <segment id="NAD" maxrepeat="1" required="true"/>
          <segment id="IFD" maxrepeat="1"/>
          <segment id="DTM" maxrepeat="99"/>
          <segment id="IDE" maxrepeat="9"/>
          <group id="SG231" maxrepeat="99">
            <segment id="CTA" maxrepeat="1" required="true"/>
            <segment id="COM" maxrepeat="99"/>
          </group>
        </group>
        <group id="SG232" maxrepeat="99">
          <segment id="LOC" maxrepeat="1" required="true"/>
          <segment id="DTM" maxrepeat="99"/>
        </group>
        <group id="SG233" maxrepeat="999">
          <segment id="PAC" maxrepeat="1" required="true"/>
          <segment id="SEQ" maxrepeat="1" required="true"/>
          <segment id="PCI" maxrepeat="99"/>
          <segment id="FTX" maxrepeat="99"/>
          <segment id="GEI" maxrepeat="99"/>
          <segment id="DIM" maxrepeat="99"/>
          <segment id="MEA" maxrepeat="99"/>
          <group id="SG234" maxrepeat="99">
            <segment id="NAD" maxrepeat="1" required="true"/>
            <segment id="IFD" maxrepeat="1"/>
            <segment id="DTM" maxrepeat="99"/>
            <segment id="IDE" maxrepeat="9"/>
            <group id="SG235" maxrepeat="99">
              <segment id="CTA" maxrepeat="1" required="true"/>
              <segment id="COM" maxrepeat="99"/>
            </group>
          </group>
        </group>
        <group id="SG236" maxrepeat="99">
          <segment id="ARR" maxrepeat="1" required="true"/>
          <segment id="FTX" maxrepeat="99"/>
          <segment id="TCC" maxrepeat="99"/>
          <group id="SG237" maxrepeat="9">
            <segment id="ATT" maxrepeat="1" required="true"/>
            <segment id="DGS" maxrepeat="1" required="true"/>
            <segment id="FTX" maxrepeat="9"/>
            <group id="SG238" maxrepeat="9">
              <segment id="NAD" maxrepeat="1" required="true"/>
              <segment id="IDE" maxrepeat="9"/>
              <group id="SG239" maxrepeat="9">
                <segment id="CTA" maxrepeat="1" required="true"/>
                <segment id="COM" maxrepeat="9"/>
              </group>
            </group>
          </group>
        </group>
      </group>
      <group id="SG240" maxrepeat="99">
        <segment id="GID" maxrepeat="1" required="true"/>
        <segment id="IMD" maxrepeat="99"/>
        <segment id="APP" maxrepeat="99"/>
        <segment id="FTX" maxrepeat="99"/>
        <segment id="RFF" maxrepeat="99"/>
        <segment id="DTM" maxrepeat="99"/>
        <segment id="GIR" maxrepeat="99"/>
        <segment id="GIN" maxrepeat="99"/>
        <segment id="GEI" maxrepeat="99"/>
        <segment id="MEA" maxrepeat="99"/>
        <segment id="MOA" maxrepeat="99"/>
        <segment id="CDI" maxrepeat="99"/>
        <segment id="PGI" maxrepeat="99"/>
        <segment id="TCC" maxrepeat="99"/>
        <segment id="CNT" maxrepeat="99"/>
        <segment id="IFD" maxrepeat="99"/>
        <segment id="TDT" maxrepeat="9"/>
        <group id="SG241" maxrepeat="99">
          <segment id="LOC" maxrepeat="1" required="true"/>
          <segment id="SEQ" maxrepeat="1" required="true"/>
          <segment id="DTM" maxrepeat="99"/>
        </group>
        <group id="SG242" maxrepeat="99">
          <segment id="NAD" maxrepeat="1" required="true"/>
          <segment id="IFD" maxrepeat="9"/>
          <segment id="DTM" maxrepeat="99"/>
          <segment id="IDE" maxrepeat="9"/>
          <group id="SG243" maxrepeat="99">
            <segment id="CTA" maxrepeat="1" required="true"/>
            <segment id="COM" maxrepeat="99"/>
          </group>
        </group>
        <group id="SG244" maxrepeat="99">
          <segment id="DOC" maxrepeat="1" required="true"/>
          <segment id="RFF" maxrepeat="99"/>
          <segment id="DTM" maxrepeat="99"/>
          <segment id="MOA" maxrepeat="99"/>
          <segment id="ALI" maxrepeat="1"/>
          <segment id="QTY" maxrepeat="99"/>
          <segment id="TSR" maxrepeat="99"/>
          <segment id="GEI" maxrepeat="9"/>
          <segment id="GIN" maxrepeat="99"/>
          <segment id="GIR" maxrepeat="99"/>
          <segment id="IMD" maxrepeat="99"/>
          <group id="SG245" maxrepeat="99">
            <segment id="NAD" maxrepeat="1" required="true"/>
            <segment id="IFD" maxrepeat="1"/>
            <segment id="IDE" maxrepeat="9"/>
            <group id="SG246" maxrepeat="99">
              <segment id="CTA" maxrepeat="1" required="true"/>
              <segment id="COM" maxrepeat="99"/>
            </group>
          </group>
          <group id="SG247" maxrepeat="99">
            <segment id="LOC" maxrepeat="1" required="true"/>
            <segment id="DTM" maxrepeat="99"/>
          </group>
        </group>
        <group id="SG248" maxrepeat="99">
          <segment id="RCS" maxrepeat="1" required="true"/>
          <segment id="FTX" maxrepeat="9"/>
          <segment id="DTM" maxrepeat="99"/>
          <segment id="GEI" maxrepeat="99"/>
          <segment id="ALI" maxrepeat="99"/>
          <group id="SG249" maxrepeat="99">
            <segment id="ERP" maxrepeat="1" required="true"/>
            <segment id="ELU" maxrepeat="99"/>
          </group>
        </group>
        <group id="SG250" maxrepeat="999">
          <segment id="PAC" maxrepeat="1" required="true"/>
          <segment id="PCI" maxrepeat="99"/>
          <segment id="FTX" maxrepeat="99"/>
          <segment id="GEI" maxrepeat="99"/>
          <segment id="DIM" maxrepeat="99"/>
          <segment id="MEA" maxrepeat="99"/>
        </group>
        <group id="SG251" maxrepeat="99">
          <segment id="COD" maxrepeat="1" required="true"/>
          <segment id="QTY" maxrepeat="99"/>
          <segment id="PCD" maxrepeat="99"/>
          <segment id="GEI" maxrepeat="99"/>
          <segment id="LOC" maxrepeat="9"/>
        </group>
        <group id="SG252" maxrepeat="1">
          <segment id="INP" maxrepeat="1" required="true"/>
          <segment id="DTM" maxrepeat="9"/>
          <segment id="LOC" maxrepeat="99"/>
          <group id="SG253" maxrepeat="1">
            <segment id="NAD" maxrepeat="1" required="true"/>
            <segment id="IFD" maxrepeat="1"/>
            <segment id="DTM" maxrepeat="99"/>
            <segment id="IDE" maxrepeat="9"/>
            <group id="SG254" maxrepeat="99">
              <segment id="CTA" maxrepeat="1" required="true"/>
              <segment id="COM" maxrepeat="99"/>
            </group>
          </group>
        </group>
        <group id="SG255" maxrepeat="99">
          <segment id="TAX" maxrepeat="1" required="true"/>
          <segment id="DTM" maxrepeat="99"/>
          <segment id="ALI" maxrepeat="99"/>
          <segment id="MOA" maxrepeat="99"/>
          <segment id="QTY" maxrepeat="99"/>
          <group id="SG256" maxrepeat="99">
            <segment id="PAI" maxrepeat="1" required="true"/>
            <segment id="RFF" maxrepeat="99"/>
            <segment id="MOA" maxrepeat="99"/>
            <segment id="DTM" maxrepeat="99"/>
            <group id="SG257" maxrepeat="99">
              <segment id="GIR" maxrepeat="1" required="true"/>
              <segment id="LOC" maxrepeat="99"/>
              <segment id="VLI" maxrepeat="1"/>
              <segment id="DTM" maxrepeat="99"/>
              <group id="SG258" maxrepeat="99">
                <segment id="NAD" maxrepeat="1" required="true"/>
                <segment id="IFD" maxrepeat="1"/>
                <segment id="DTM" maxrepeat="99"/>
                <segment id="IDE" maxrepeat="9"/>
                <group id="SG259" maxrepeat="99">
                  <segment id="CTA" maxrepeat="1" required="true"/>
                  <segment id="COM" maxrepeat="99"/>
                </group>
              </group>
            </group>
          </group>
        </group>
        <group id="SG260" maxrepeat="99">
          <segment id="DLI" maxrepeat="1" required="true"/>
          <segment id="MOA" maxrepeat="99"/>
        </group>
        <group id="SG261" maxrepeat="99">
          <segment id="STS" maxrepeat="1" required="true"/>
          <segment id="DTM" maxrepeat="99"/>
          <group id="SG262" maxrepeat="99">
            <segment id="ERP" maxrepeat="1" required="true"/>
            <segment id="ELU" maxrepeat="99"/>
          </group>
        </group>
        <group id="SG263" maxrepeat="99">
          <segment id="TMP" maxrepeat="1" required="true"/>
          <segment id="MEA" maxrepeat="99"/>
          <segment id="DGS" maxrepeat="99"/>
        </group>
        <group id="SG264" maxrepeat="99">
          <segment id="EQD" maxrepeat="1" required="true"/>
          <segment id="SEQ" maxrepeat="1" required="true"/>
        </group>
        <group id="SG265" maxrepeat="99">
          <segment id="PRC" maxrepeat="1" required="true"/>
          <segment id="SEQ" maxrepeat="1" required="true"/>
          <segment id="TMP" maxrepeat="9"/>
          <segment id="DTM" maxrepeat="9"/>
          <group id="SG266" maxrepeat="99">
            <segment id="NAD" maxrepeat="1" required="true"/>
            <segment id="IFD" maxrepeat="1"/>
            <segment id="IDE" maxrepeat="9"/>
            <group id="SG267" maxrepeat="99">
              <segment id="CTA" maxrepeat="1" required="true"/>
              <segment id="COM" maxrepeat="99"/>
            </group>
          </group>
        </group>
        <group id="SG268" maxrepeat="9">
          <segment id="ATT" maxrepeat="1" required="true"/>
          <segment id="DGS" maxrepeat="1" required="true"/>
          <segment id="FTX" maxrepeat="9"/>
          <segment id="PAC" maxrepeat="9"/>
          <segment id="MEA" maxrepeat="9"/>
          <group id="SG269" maxrepeat="9">
            <segment id="NAD" maxrepeat="1" required="true"/>
            <segment id="IDE" maxrepeat="9"/>
            <group id="SG270" maxrepeat="9">
              <segment id="CTA" maxrepeat="1" required="true"/>
              <segment id="COM" maxrepeat="9"/>
            </group>
          </group>
        </group>
      </group>
      <group id="SG271" maxrepeat="99">
        <segment id="TOD" maxrepeat="1" required="true"/>
        <segment id="RTE" maxrepeat="1"/>
        <segment id="MOA" maxrepeat="1"/>
      </group>
    </group>
    <group id="SG272" maxrepeat="9999">
      <segment id="LIN" maxrepeat="1" required="true"/>
      <segment id="MOA" maxrepeat="99"/>
      <segment id="IFD" maxrepeat="99"/>
      <segment id="STS" maxrepeat="99"/>
      <group id="SG273" maxrepeat="99">
        <segment id="NAD" maxrepeat="1" required="true"/>
        <segment id="IFD" maxrepeat="1"/>
        <segment id="DTM" maxrepeat="99"/>
        <segment id="IDE" maxrepeat="9"/>
        <group id="SG274" maxrepeat="99">
          <segment id="CTA" maxrepeat="1" required="true"/>
          <segment id="COM" maxrepeat="99"/>
        </group>
      </group>
      <group id="SG275" maxrepeat="99">
        <segment id="LOC" maxrepeat="1" required="true"/>
        <segment id="DTM" maxrepeat="99"/>
      </group>
      <group id="SG276" maxrepeat="99">
        <segment id="DOC" maxrepeat="1" required="true"/>
        <segment id="RFF" maxrepeat="99"/>
        <segment id="DTM" maxrepeat="99"/>
        <segment id="MOA" maxrepeat="99"/>
        <segment id="ALI" maxrepeat="1"/>
        <segment id="QTY" maxrepeat="99"/>
        <segment id="TSR" maxrepeat="99"/>
        <group id="SG277" maxrepeat="99">
          <segment id="NAD" maxrepeat="1" required="true"/>
          <segment id="IFD" maxrepeat="1"/>
          <segment id="IDE" maxrepeat="9"/>
          <group id="SG278" maxrepeat="99">
            <segment id="CTA" maxrepeat="1" required="true"/>
            <segment id="COM" maxrepeat="99"/>
          </group>
        </group>
        <group id="SG279" maxrepeat="99">
          <segment id="LOC" maxrepeat="1" required="true"/>
          <segment id="DTM" maxrepeat="99"/>
        </group>
      </group>
      <group id="SG280" maxrepeat="99">
        <segment id="RCS" maxrepeat="1" required="true"/>
        <segment id="FTX" maxrepeat="9"/>
        <segment id="DTM" maxrepeat="99"/>
        <segment id="GEI" maxrepeat="99"/>
        <segment id="ALI" maxrepeat="99"/>
        <group id="SG281" maxrepeat="99">
          <segment id="ERP" maxrepeat="1" required="true"/>
          <segment id="ELU" maxrepeat="99"/>
          <segment id="ARR" maxrepeat="99"/>
        </group>
      </group>
      <group id="SG282" maxrepeat="1">
        <segment id="INP" maxrepeat="1" required="true"/>
        <segment id="DTM" maxrepeat="9"/>
        <segment id="LOC" maxrepeat="99"/>
        <group id="SG283" maxrepeat="1">
          <segment id="NAD" maxrepeat="1" required="true"/>
          <segment id="IFD" maxrepeat="1"/>
          <segment id="DTM" maxrepeat="99"/>
          <segment id="IDE" maxrepeat="9"/>
          <group id="SG284" maxrepeat="99">
            <segment id="CTA" maxrepeat="1" required="true"/>
            <segment id="COM" maxrepeat="99"/>
          </group>
        </group>
      </group>
      <group id="SG285" maxrepeat="99">
        <segment id="MEA" maxrepeat="1" required="true"/>
        <segment id="QTY" maxrepeat="99"/>
      </group>
      <group id="SG286" maxrepeat="99">
        <segment id="PAC" maxrepeat="1" required="true"/>
        <segment id="SEQ" maxrepeat="1" required="true"/>
        <segment id="PCI" maxrepeat="99"/>
        <segment id="FTX" maxrepeat="99"/>
        <segment id="GEI" maxrepeat="99"/>
        <segment id="DIM" maxrepeat="99"/>
        <segment id="MEA" maxrepeat="99"/>
      </group>
      <group id="SG287" maxrepeat="99">
        <segment id="ARD" maxrepeat="1" required="true"/>
        <segment id="MOA" maxrepeat="99"/>
        <segment id="GEI" maxrepeat="99"/>
        <segment id="PCD" maxrepeat="99"/>
      </group>
    </group>
    <group id="SG288" maxrepeat="9999">
      <segment id="ASI" maxrepeat="1" required="true"/>
      <segment id="CNI" maxrepeat="1" required="true"/>
      <segment id="RFF" maxrepeat="99"/>
      <segment id="MOA" maxrepeat="99"/>
      <segment id="CNT" maxrepeat="9"/>
      <segment id="TOD" maxrepeat="99"/>
      <segment id="GEI" maxrepeat="99"/>
      <group id="SG289" maxrepeat="99">
        <segment id="NAD" maxrepeat="1" required="true"/>
        <segment id="IDE" maxrepeat="9"/>
        <group id="SG290" maxrepeat="99">
          <segment id="CTA" maxrepeat="1" required="true"/>
          <segment id="COM" maxrepeat="99"/>
        </group>
      </group>
      <group id="SG291" maxrepeat="99">
        <segment id="LOC" maxrepeat="1" required="true"/>
        <segment id="SEQ" maxrepeat="1" required="true"/>
        <segment id="ADR" maxrepeat="9"/>
      </group>
      <group id="SG292" maxrepeat="99">
        <segment id="DOC" maxrepeat="1" required="true"/>
        <segment id="RFF" maxrepeat="99"/>
        <segment id="DTM" maxrepeat="99"/>
      </group>
      <group id="SG293" maxrepeat="9999">
        <segment id="EQD" maxrepeat="1" required="true"/>
        <segment id="SEQ" maxrepeat="1" required="true"/>
        <segment id="QTY" maxrepeat="1"/>
        <group id="SG294" maxrepeat="99">
          <segment id="SEL" maxrepeat="1" required="true"/>
          <segment id="SEQ" maxrepeat="1" required="true"/>
        </group>
      </group>
      <group id="SG295" maxrepeat="99">
        <segment id="TDT" maxrepeat="1" required="true"/>
        <group id="SG296" maxrepeat="99">
          <segment id="LOC" maxrepeat="1" required="true"/>
          <segment id="SEQ" maxrepeat="1" required="true"/>
        </group>
      </group>
      <group id="SG297" maxrepeat="9999">
        <segment id="SEQ" maxrepeat="1" required="true"/>
        <segment id="RFF" maxrepeat="99"/>
        <segment id="TDT" maxrepeat="9"/>
        <segment id="MOA" maxrepeat="9"/>
        <segment id="MEA" maxrepeat="99"/>
        <segment id="TOD" maxrepeat="99"/>
        <segment id="LOC" maxrepeat="99"/>
        <group id="SG298" maxrepeat="99">
          <segment id="NAD" maxrepeat="1" required="true"/>
          <segment id="IFD" maxrepeat="1"/>
          <segment id="IDE" maxrepeat="9"/>
          <group id="SG299" maxrepeat="99">
            <segment id="CTA" maxrepeat="1" required="true"/>
            <segment id="COM" maxrepeat="99"/>
          </group>
        </group>
        <group id="SG300" maxrepeat="99">
          <segment id="DOC" maxrepeat="1" required="true"/>
          <segment id="RFF" maxrepeat="99"/>
          <segment id="DTM" maxrepeat="99"/>
        </group>
        <group id="SG301" maxrepeat="99">
          <segment id="RCS" maxrepeat="1" required="true"/>
          <segment id="FTX" maxrepeat="9"/>
        </group>
        <group id="SG302" maxrepeat="999">
          <segment id="PAC" maxrepeat="1" required="true"/>
          <segment id="SEQ" maxrepeat="1" required="true"/>
          <segment id="PCI" maxrepeat="99"/>
        </group>
        <group id="SG303" maxrepeat="9999">
          <segment id="EQD" maxrepeat="1" required="true"/>
          <segment id="SEQ" maxrepeat="1" required="true"/>
        </group>
        <group id="SG304" maxrepeat="99">
          <segment id="GID" maxrepeat="1" required="true"/>
          <segment id="IMD" maxrepeat="99"/>
          <segment id="TCC" maxrepeat="99"/>
          <group id="SG305" maxrepeat="99">
            <segment id="TMP" maxrepeat="1" required="true"/>
            <segment id="DGS" maxrepeat="99"/>
          </group>
        </group>
      </group>
      <group id="SG306" maxrepeat="9999">
        <segment id="DMS" maxrepeat="1" required="true"/>
        <segment id="SEQ" maxrepeat="1" required="true"/>
        <group id="SG307" maxrepeat="99">
          <segment id="NAD" maxrepeat="1" required="true"/>
          <segment id="IDE" maxrepeat="9"/>
          <group id="SG308" maxrepeat="99">
            <segment id="CTA" maxrepeat="1" required="true"/>
            <segment id="COM" maxrepeat="99"/>
          </group>
        </group>
        <group id="SG309" maxrepeat="9999">
          <segment id="LIN" maxrepeat="1" required="true"/>
          <group id="SG310" maxrepeat="99">
            <segment id="NAD" maxrepeat="1" required="true"/>
            <segment id="IDE" maxrepeat="9"/>
            <group id="SG311" maxrepeat="99">
              <segment id="CTA" maxrepeat="1" required="true"/>
              <segment id="COM" maxrepeat="99"/>
            </group>
          </group>
          <group id="SG312" maxrepeat="99">
            <segment id="GID" maxrepeat="1" required="true"/>
            <segment id="TCC" maxrepeat="99"/>
          </group>
        </group>
      </group>
    </group>
  </group>
  <segment id="UNS" maxrepeat="1" required="true"/>
  <segment id="AUT" maxrepeat="1"/>
  <segment id="CNT" maxrepeat="9"/>
  <segment id="UNT" maxrepeat="1" required="true"/>
</message>
